flaskquotes/__init__.py
flaskquotes/afi.py
flaskquotes/app.py
flaskquotes/console.py
flaskquotes/version.py
flaskquotes-1.0.9.dist-info/LICENSE
flaskquotes-1.0.9.dist-info/METADATA
flaskquotes-1.0.9.dist-info/WHEEL
flaskquotes-1.0.9.dist-info/entry_points.txt
flaskquotes-1.0.9.dist-info/top_level.txt
flaskquotes-1.0.9.dist-info/RECORD
