Metadata-Version: 2.1
Name: flaskquotes
Version: 1.0.9
Summary: Get AFI top 100 quotes
Home-page: UNKNOWN
Author: Jeff Moorhead
Author-email: jeff.moorhead1@gmail.com
License: UNKNOWN
Platform: UNKNOWN
Requires-Dist: BeautifulSoup4
Requires-Dist: Flask
